modellock.cpython-310-x86_64-linux-gnu.so
modellock.pyi
modellock_serving.cpython-310-x86_64-linux-gnu.so
modellock_serving.pyi
modellock/lock/content.lock
modellock/lock/content.lock.enc
modellock-0.2.0.dist-info/METADATA
modellock-0.2.0.dist-info/WHEEL
modellock-0.2.0.dist-info/entry_points.txt
modellock-0.2.0.dist-info/top_level.txt
modellock-0.2.0.dist-info/RECORD
modellock-0.2.0.dist-info/licenses/LICENSE
