Metadata-Version: 2.4
Name: modellock
Version: 0.2.0
Summary: AI 模型加密保护与授权系统
Author-email: Yaqiang Sun <sunyaking@163.com>
Requires-Python: <3.14,>=3.10
License-File: LICENSE
Requires-Dist: pycryptodome>=3.23.0
Requires-Dist: psutil>=5.9.0
Requires-Dist: fastapi>=0.68.0
Requires-Dist: uvicorn>=0.15.0
Requires-Dist: pycryptodome>=3.10.1
Requires-Dist: modellock>=0.0.1
Requires-Dist: python-multipart>=0.0.20
Requires-Dist: requests>=2.32.5
Dynamic: license-file
